clientfactory/__init__.py
clientfactory/logs.py
clientfactory/auths/__init__.py
clientfactory/auths/dpop.py
clientfactory/auths/jwt.py
clientfactory/backends/__init__.py
clientfactory/backends/algolia.py
clientfactory/backends/elasticsearch.py
clientfactory/backends/gateway.py
clientfactory/backends/graphql.py
clientfactory/core/__init__.py
clientfactory/core/backend.py
clientfactory/core/client.py
clientfactory/core/persistence.py
clientfactory/core/resource.py
clientfactory/core/session.py
clientfactory/core/bases/__init__.py
clientfactory/core/bases/auth.py
clientfactory/core/bases/backend.py
clientfactory/core/bases/client.py
clientfactory/core/bases/condition.py
clientfactory/core/bases/declarative.py
clientfactory/core/bases/engine.py
clientfactory/core/bases/persistence.py
clientfactory/core/bases/resource.py
clientfactory/core/bases/session.py
clientfactory/core/metas/__init__.py
clientfactory/core/metas/declarative.py
clientfactory/core/metas/protocoled.py
clientfactory/core/models/__init__.py
clientfactory/core/models/config.py
clientfactory/core/models/contexts.py
clientfactory/core/models/enums.py
clientfactory/core/models/methods.py
clientfactory/core/models/request.py
clientfactory/core/protos/__init__.py
clientfactory/core/protos/auth.py
clientfactory/core/protos/backend.py
clientfactory/core/protos/boundmethod.py
clientfactory/core/protos/condition.py
clientfactory/core/protos/payload.py
clientfactory/core/protos/persistence.py
clientfactory/core/protos/request/__init__.py
clientfactory/core/protos/request/engine.py
clientfactory/core/protos/request/lifecycle.py
clientfactory/core/utils/__init__.py
clientfactory/core/utils/discover/__init__.py
clientfactory/core/utils/discover/binding.py
clientfactory/core/utils/discover/collect.py
clientfactory/core/utils/parameters/__init__.py
clientfactory/core/utils/parameters/construct.py
clientfactory/core/utils/request/__init__.py
clientfactory/core/utils/request/building.py
clientfactory-0.9.38.dist-info/METADATA
clientfactory-0.9.38.dist-info/WHEEL
clientfactory-0.9.38.dist-info/RECORD
