Metadata-Version: 2.4
Name: clientfactory
Version: 0.9.38
Summary: A declarative framework for building API clients with minimal boilerplate using decorators, authentication, and backend adapters
Project-URL: Homepage, https://github.com/schizoprada/clientfactory
Project-URL: Repository, https://github.com/schizoprada/clientfactory
Project-URL: Bug Tracker, https://github.com/schizoprada/clientfactory/issues
Project-URL: Changelog, https://github.com/schizoprada/clientfactory/blob/main/docs/CHANGELOG.md
Author-email: Joel Yisrael <schizoprada@gmail.com>
Maintainer-email: Joel Yisrael <schizoprada@gmail.com>
License: MIT
Keywords: adapter,algolia,api,authentication,backend,client,declarative,decorators,dpop,framework,graphql,http,jwt,pydantic,requests
Classifier: Development Status :: 3 - Alpha
Classifier: Intended Audience :: Developers
Classifier: License :: OSI Approved :: MIT License
Classifier: Operating System :: OS Independent
Classifier: Programming Language :: Python :: 3
Classifier: Programming Language :: Python :: 3.13
Classifier: Topic :: Internet :: WWW/HTTP :: Dynamic Content
Classifier: Topic :: Software Development :: Libraries :: Python Modules
Classifier: Topic :: Text Processing
Classifier: Topic :: Utilities
Requires-Python: >=3.13
Requires-Dist: colorama>=0.4.6
Requires-Dist: cryptography>=45.0.4
Requires-Dist: pydantic>=2.11.5
Requires-Dist: pyjwt>=2.10.1
Requires-Dist: requests>=2.32.3
Requires-Dist: schematix>=0.4.63
Provides-Extra: dataclasses
Requires-Dist: dataclasses-json>=0.5.0; extra == 'dataclasses'
Provides-Extra: dev
Requires-Dist: black>=23.0.0; extra == 'dev'
Requires-Dist: flake8>=6.0.0; extra == 'dev'
Requires-Dist: isort>=5.12.0; extra == 'dev'
Requires-Dist: mypy>=1.0.0; extra == 'dev'
Requires-Dist: pre-commit>=3.0.0; extra == 'dev'
Requires-Dist: pytest-cov>=4.0.0; extra == 'dev'
Requires-Dist: pytest>=7.0.0; extra == 'dev'
Provides-Extra: docs
Requires-Dist: mkdocs-material>=9.0.0; extra == 'docs'
Requires-Dist: mkdocs>=1.5.0; extra == 'docs'
Requires-Dist: mkdocstrings[python]>=0.22.0; extra == 'docs'
Provides-Extra: test
Requires-Dist: pytest-cov>=4.0.0; extra == 'test'
Requires-Dist: pytest-xdist>=3.0.0; extra == 'test'
Requires-Dist: pytest>=7.0.0; extra == 'test'
